neko/__init__.py
neko/_annotations/.ipynb_checkpoints/gene_ontology-checkpoint.py
neko/_annotations/__init__.py
neko/_annotations/gene_ontology.py
neko/_metadata.py
neko/_methods/.ipynb_checkpoints/enrichment_methods-checkpoint.py
neko/_methods/__init__.py
neko/_methods/compare.py
neko/_methods/enrichment_methods.py
neko/_outputs/__init__.py
neko/_outputs/exports.py
neko/_visual/__init__.py
neko/_visual/history.py
neko/_visual/visualize_network.py
neko/core/__init__.py
neko/core/algorithms/graph_traversal.py
neko/core/edge.py
neko/core/network.py
neko/core/network_state.py
neko/core/node.py
neko/core/strategies.py
neko/core/tools.py
neko/data/__init__.py
neko/inputs/__init__.py
neko/inputs/_db/_misc.py
neko/inputs/_db/huri.py
neko/inputs/_db/omnipath.py
neko/inputs/_db/psp.py
neko/inputs/_db/signor.py
neko/inputs/_def.py
neko/inputs/_misc.py
neko/inputs/_universe.py
neko/inputs/db_translator.py
neko/inputs/test_db_translator.py
nekomata-1.1.0.dist-info/METADATA
nekomata-1.1.0.dist-info/WHEEL
nekomata-1.1.0.dist-info/licenses/LICENSE
nekomata-1.1.0.dist-info/RECORD
