Metadata-Version: 2.4
Name: nekomata
Version: 1.1.0
Summary: Package to extract, visualize, convert and study interactions from database into executable activity flow based model
License: GNU General Public License Version 3
License-File: LICENSE
Author: Marco Ruscone
Author-email: marco.ruscone@curie.fr
Requires-Python: >=3.10,<4.0
Classifier: Development Status :: 2 - Pre-Alpha
Classifier: Intended Audience :: Developers
Classifier: Intended Audience :: Science/Research
Classifier: License :: OSI Approved :: GNU General Public License v3 (GPLv3)
Classifier: License :: Other/Proprietary License
Classifier: Natural Language :: English
Classifier: Operating System :: OS Independent
Classifier: Programming Language :: Python
Classifier: Programming Language :: Python :: 3
Classifier: Programming Language :: Python :: 3.10
Classifier: Programming Language :: Python :: 3.11
Classifier: Programming Language :: Python :: 3.12
Classifier: Programming Language :: Python :: 3.13
Classifier: Programming Language :: Python :: 3.14
Classifier: Topic :: Scientific/Engineering :: Bio-Informatics
Requires-Dist: graphviz
Requires-Dist: jupyterlab
Requires-Dist: networkx
Requires-Dist: notebook
Requires-Dist: omnipath (==1.0.9)
Requires-Dist: pandas (==2.2.2)
Requires-Dist: paramiko (<4.0.0)
Requires-Dist: pycurl
Requires-Dist: pypath-common (>=0.2.5,<0.3.0)
Requires-Dist: pypath-omnipath (==0.16.20)
Requires-Dist: toml
Requires-Dist: unipressed
Requires-Dist: yfiles_jupyter_graphs
Project-URL: Bug Tracker, https://github.com/sysbio-curie/Neko/issues
Project-URL: Documentation, https://sysbio-curie.github.io/Neko/
Project-URL: Homepage, https://github.com/sysbio-curie/Neko
Project-URL: Repository, https://github.com/sysbio-curie/Neko
